README.rst
setup.py
myhdl_lib/__init__.py
myhdl_lib/arbiter.py
myhdl_lib/fifo.py
myhdl_lib/fifo_async.py
myhdl_lib/fifo_speculative.py
myhdl_lib/handshake.py
myhdl_lib/mem.py
myhdl_lib/mux.py
myhdl_lib/pipeline_control.py
myhdl_lib/sfifo_beh.py
myhdl_lib/stream.py
myhdl_lib/utils.py
myhdl_lib.egg-info/PKG-INFO
myhdl_lib.egg-info/SOURCES.txt
myhdl_lib.egg-info/dependency_links.txt
myhdl_lib.egg-info/not-zip-safe
myhdl_lib.egg-info/requires.txt
myhdl_lib.egg-info/top_level.txt
myhdl_lib/simulation/_DUTer.py
myhdl_lib/simulation/__init__.py
myhdl_lib/simulation/clock.py
myhdl_lib/simulation/payload_generator.py
myhdl_lib/simulation/reset.py
myhdl_lib/simulation/utils.py
test/test_arbiter_priority.py
test/test_arbiter_roundrobin.py
test/test_bitslice_select.py
test/test_bytecount.py
test/test_byteorder.py
test/test_byteslice_select.py
test/test_checksum.py
test/test_demux.py
test/test_fifo.py
test/test_fifo_async.py
test/test_fifo_speculative.py
test/test_hs_arbdemux.py
test/test_hs_arbmux.py
test/test_hs_demux.py
test/test_hs_fork.py
test/test_hs_join.py
test/test_hs_mux.py
test/test_ls_demux.py
test/test_ls_mux.py
test/test_mem.py
test/test_mux.py
test/test_payload_generator.py
test/test_pipeline_control.py