Metadata-Version: 1.1
Name: myhdl-lib
Version: 0.1.0
Summary: TODO: Library of components based on Python and MyHDL
Home-page: https://github.com/nkavaldj/myhdl_lib.git
Author: Nikolay Kavaldjiev
Author-email: nikolay.kavaldjiev@gmail.com
License: MIT
Keywords: myhdl pihdf fpga
Platform: UNKNOWN
Classifier: Development Status :: 3 - Alpha
Classifier: License :: OSI Approved :: MIT License
Classifier: Programming Language :: Python :: 2.7
Classifier: Topic :: Scientific/Engineering :: Electronic Design Automation (EDA)
